{"status":"done","publicPath":"http://192.168.33.12:8080/","chunks":{"about":[{"name":"static/js/about.js","publicPath":"http://192.168.33.12:8080/static/js/about.js","path":"/home/vagrant/bandue/client/bundles/static/js/about.js"}],"index":[{"name":"static/js/index.js","publicPath":"http://192.168.33.12:8080/static/js/index.js","path":"/home/vagrant/bandue/client/bundles/static/js/index.js"},{"name":"index.85a7e32c017b51d9211e.hot-update.js","publicPath":"http://192.168.33.12:8080/index.85a7e32c017b51d9211e.hot-update.js","path":"/home/vagrant/bandue/client/bundles/index.85a7e32c017b51d9211e.hot-update.js"}],"register":[{"name":"static/js/register.js","publicPath":"http://192.168.33.12:8080/static/js/register.js","path":"/home/vagrant/bandue/client/bundles/static/js/register.js"}]},"error":"ModuleError","message":"Module Error (from ./node_modules/eslint-loader/index.js):\n\n/home/vagrant/bandue/client/src/components/common/Sidebar.vue\n  101:24  error  Expected '!==' and instead saw '!='  eqeqeq\n\n✖ 1 problem (1 error, 0 warnings)\n"}